Metadata-Version: 2.1
Name: codigoMorse
Version: 1.1
Summary: Codificador/Descodificador Morse
Home-page: UNKNOWN
Author: Oscar B.
Author-email: oscarjr01.13@gtmail.com
License: GPLv3
Platform: UNKNOWN
Classifier: Programming Language :: Python :: 3
Classifier: License :: OSI Approved :: GNU General Public License v3 (GPLv3)
Classifier: Development Status :: 4 - Beta
Classifier: Intended Audience :: Developers
Classifier: Operating System :: OS Independent
